freetranslate/__init__.py
freetranslate/bingtranslator.py
freetranslate/constants.py
freetranslate/googletranslate.py
freetranslate/googlewebtranslate.py
freetranslate/libretranslate.py
freetranslate/translateresult.py
freetranslate/translatorabc.py
freetranslate-0.2.2.dist-info/LICENSE
freetranslate-0.2.2.dist-info/METADATA
freetranslate-0.2.2.dist-info/WHEEL
freetranslate-0.2.2.dist-info/top_level.txt
freetranslate-0.2.2.dist-info/RECORD
