Metadata-Version: 2.1
Name: freetranslate
Version: 0.2.2
Summary: Another translate API for Python.
Home-page: https://gitlab.com/tretrauit/freetranslate
Author: tretrauit
Author-email: tretrauit@gmail.com
License: MIT
Platform: UNKNOWN
Classifier: License :: OSI Approved :: MIT License
Classifier: Programming Language :: Python :: 3
License-File: LICENSE
Requires-Dist: aiohttp
